open_source_pdks/__init__.py
open_source_pdks-0.0.0.dist-info/LICENSE
open_source_pdks-0.0.0.dist-info/METADATA
open_source_pdks-0.0.0.dist-info/WHEEL
open_source_pdks-0.0.0.dist-info/top_level.txt
open_source_pdks-0.0.0.dist-info/RECORD
