Metadata-Version: 2.1
Name: open-source-pdks
Version: 0.0.0
Summary: Python API for decoding information about Google's open source process design kits (PDKs).
Author-email: Tim 'mithro' Ansell <tansell@google.com>
License: 
Project-URL: Homepage, https://github.com/google/open-source-pdks
Project-URL: Bug Tracker, https://github.com/google/open-source-pdks/issues
Classifier: Programming Language :: Python :: 3
Classifier: License :: OSI Approved :: Apache Software License
Classifier: Operating System :: OS Independent
Requires-Python: >=3.7
License-File: LICENSE
